{
  "fieldsList": {
    "flatHierarchyBox": "Oszlopok kiválasztása és rendezése",
    "hierarchyBox": "Húzza ide a dimenziókat!",
    "filterBox": "Húzza ide, és rendezze a riport szűrőket!",
    "rowBox": "Húzza ide, és rendezze a sorokat!",
    "columnBox": "Húzza ide, és rendezze az oszlopokat!",
    "measureBox": "Húzza ide, és rendezze az értékeket!",
    "values": "Értékek",
    "addCalculatedMeasure": "Kalkulált érték hozzáadása",
    "expandAll": "Összes kinyitása",
    "collapseAll": "Összes összecsukása",
    "formulasGroupName": "Kalkulált érték",
    "allFields": "Összes kimutatásmező",
    "rows": "Sorok",
    "columns": "Oszlopok",
    "filters": "Szűrők",
    "dropField": "Húzza ide a mezőket!",
    "title": "Kimutatásmezők",
    "subtitle": "Húzza be, és rendezze a mezőket!"
  },
  "filter": {
    "all": "Minden",
    "multipleItems": "Több elem kijelölése",
    "selectAll": "Összes kiválasztása",
    "selectAllResults": "Összes eredmény kiválasztása",
    "top": "Első",
    "bottom": "Utolsó",
    "ascSort": "A-Z",
    "descSort": "Z-A",
    "measuresPrompt": "Válasszon értéket",
    "search": "Keresés",
    "amountSelected": "A(z) {1} elemből {0} kiválasztva",
    "amountFound": "A(z) {1} talált elemből {0} kiválasztva",
    "sort": "Rendezés",
    "filterBy": "Szűrés vlami alapján:",
    "labelsFilter": "Címkék",
    "numbersFilter": "Címkék",
    "valuesFilter": "Értékek",
    "datesFilter": "Időpontok",
    "timeFilter": "Idő",
    "equal": "Egyenlő",
    "notEqual": "Nem egyenlő",
    "before": "Előtt",
    "beforeEqual": "Előtt vagy egyenlő",
    "after": "Után",
    "afterEqual": "Után vagy egyenlő",
    "between": "Között",
    "notBetween": "Nem között",
    "last": "Utolsó...",
    "current": "Jelenlegi...",
    "next": "Következő...",
    "begin": "Kezdődik",
    "notBegin": "Nem kezdődik",
    "end": "Vég",
    "notEnd": "Nem ér véget",
    "contain": "Tartalmaz",
    "notContain": "Nem tartalmaz",
    "greater": "Greater",
    "greaterEqual": "Nagyobb vagy egyenlő",
    "less": "Kevésbé",
    "lessEqual": "Kevesebb vagy egyenlő",
    "day": "Nap",
    "week": "Hét",
    "month": "Hónap",
    "quarter": "Negyed",
    "year": "Év",
    "seconds": "más.",
    "minutes": "per.",
    "hours": "ór.",
    "days": "nap.",
    "clearDateFilter": "Törölje a dátumszűrőt",
    "clearLabelFilter": "Törölje a címke szűrőt",
    "clearNumberFilter": "Törölje a címke szűrőt",
    "clearTimeFilter": "Tiszta időszűrő",
    "clearValueFilter": "Tiszta érték szűrő"
  },
  "drillThrough": {
    "title": "Részletek",
    "row": "Sor: <b>{0}</b>",
    "column": "Oszlop: <b>{0}</b>",
    "value": "{0}: <b>{1}</b>"
  },
  "calculatedView": {
    "title": "Kalkulált értékek",
    "measureBox": "Húzza az értékeket a képletbe",
    "measureName": "Érték neve",
    "formula": "Képlet",
    "formulaPrompt": "Húzza ide az értékeket, és szerkessze meg a képletet!",
    "calculateIndividualValues": "Kalkulált egyedi érték",
    "removeValue": "Törlés",
    "removeValueTitle": "Törli a {0}-t?",
    "removeValueMessage": "Biztos benne, hogy töröli ezt a kalkulált értéket?",
    "header": "Kalkulált érték hozzáadása",
    "allValues": "Minden érték"
  },
  "grid": {
    "total": "Összeg",
    "totals": "Összegek",
    "grandTotal": "Összesen",
    "blankMember": "(üres)",
    "dateInvalidCaption": "Érvénytelen dátum",
    "reportInformation": "Riport információ"
  },
  "charts": {
    "showLegend": "Előzmények mutatása",
    "hideLegend": "Előzmények elrejtése",
    "selectMeasures": "Válassza ki a mértéket!",
    "rowNumber": "Sor száma",
    "flatTypesLimitation": "Denormalizált táblához nem készíthető oszlop- vagy vonaldiagram",
    "noDataTitle": "Nincs megjeleníthető adat",
    "noMeasuresTitle": "Nincs megjeleníthető intézkedés. Adjon hozzá legalább egy intézkedést a Mezőlistában.",
    "bigDataSetWarning": "A kiválasztott adat túl nagy ahhoz, hogy megjelenjen a diagramon. Az adathalmaz a diagram méreteihez igazodva levágásra fog kerülni."
  },
  "tooltips": {
    "fieldList": "Kattintson a mezők megnyitásához",
    "selectAggregation": "Válassza ki az összesítést",
    "editCalculatedMeasure": "Számított érték szerkesztése",
    "row": "Sor:",
    "column": "Oszlop:",
    "headerResize": "Kívánt méretre igazítás",
    "headerFit": "Dupla kattintással tartalomhoz igazít",
    "filterIcon": "Szűrés",
    "filtered": "Szűrt",
    "expandIcon": "Kattintson a kinyitáshoz",
    "collapseIcon": "Kattintson az összecsukáshoz",
    "drillDown": "Lejjebb lépés egy hierarchiai szinttel",
    "drillUp": "Feljebb lépés egy hierarchiai szinttel",
    "sortIcon": "Kattintson a rendezéshez",
    "sortedDescIcon": "Csökkenő sorrendbe rendezés",
    "sortedAscIcon": "Növekvő sorrendbe rendezés",
    "unsortedIcon": "Kattintson a szortírozáshoz",
    "close": "Bezárás"
  },
  "aggregations": {
    "sum": {
      "caption": "Összeg",
      "totalCaption": "{0} összege",
      "grandTotalCaption": "{0} összege"
    },
    "count": {
      "caption": "Darabszám",
      "totalCaption": "{0} darabszáma",
      "grandTotalCaption": "{0} teljes darabszáma"
    },
    "distinctCount": {
      "caption": "Egyedi elemek darabszáma",
      "totalCaption": "{0} egyedi elemek darabszáma",
      "grandTotalCaption": "{0} egyedi elemek teljes darabszáma"
    },
    "differenceOfColumn": {
      "caption": "Oszlopok különbsége",
      "totalCaption": "{0} oszlopok különbsége",
      "grandTotalCaption": "{0} teljes oszlopok különbsége"
    },
    "differenceOfRow": {
      "caption": "Sorok különbsége",
      "totalCaption": "{0} sorok különbsége",
      "grandTotalCaption": "{0} teljes sorok különbsége"
    },
    "percentDifferenceOfColumn": {
      "caption": "Oszlopok különbség százalékban",
      "totalCaption": "{0} oszlopok különbség százalékban",
      "grandTotalCaption": "{0} oszlopok különbség százalékban"
    },
    "percentDifferenceOfRow": {
      "caption": "Sorok különbsége százalékban",
      "totalCaption": "{0} sorok különbsége százalékban",
      "grandTotalCaption": "{0} teljes sorok különbsége százalékban"
    },
    "average": {
      "caption": "Átlag",
      "totalCaption": "{0} átlaga",
      "grandTotalCaption": "{0} teljes átlaga"
    },
    "median": {
      "caption": "Középső",
      "totalCaption": "{0} ár mediánja",
      "grandTotalCaption": "{0} ár teljes mediánja"
    },
    "stdevp": {
      "caption": "Népesség StDev",
      "totalCaption": "{0} népesség StDev",
      "grandTotalCaption": "{0} teljes népesség StDev"
    },
    "stdevs": {
      "caption": "Minta StDev",
      "totalCaption": "{0} minta StDev",
      "grandTotalCaption": "{0} teljes minta StDev"
    },
    "product": {
      "caption": "Szorzat",
      "totalCaption": "{0} szorzata",
      "grandTotalCaption": "{0} teljes szorzata"
    },
    "min": {
      "caption": "Minimum",
      "totalCaption": "{0} minimuma",
      "grandTotalCaption": "{0} teljes minimuma"
    },
    "max": {
      "caption": "Maximum",
      "totalCaption": "{0} maximuma",
      "grandTotalCaption": "{0} teljes maximuma"
    },
    "percent": {
      "caption": "Összesen százalékban",
      "totalCaption": "{0} összesen százalékban",
      "grandTotalCaption": "{0} összesen százalékban"
    },
    "percentOfColumn": {
      "caption": "Oszlopok értéke százalékban",
      "totalCaption": "{0} oszlopok értéke százalékban",
      "grandTotalCaption": "{0} oszlopok értéke százalékban"
    },
    "percentOfRow": {
      "caption": "Sorok értéke százalékban",
      "totalCaption": "{0} sorok értéke százalékban",
      "grandTotalCaption": "{0} sorok értéke százalékban"
    },
    "percentOfParentRowTotal": {
      "caption": "a szülő sor százaléka",
      "totalCaption": "a szülő sor százaléka {0}",
      "grandTotalCaption": "a szülő sor százaléka {0}"
    },
    "percentOfParentColumnTotal": {
      "caption": "Oszlopok értéke százalékban",
      "totalCaption": "a szülő oszlop százaléka {0}",
      "grandTotalCaption": "a szülő oszlop százaléka {0}"
    },
    "runningTotalsOfColumn": {
      "caption": "Oszlopok futó összesítések",
      "totalCaption": "{0} oszlopok futó összesítések",
      "grandTotalCaption": "{0} oszlopok futó összesítések"
    },
    "runningTotalsOfRow": {
      "caption": "Sorok futó összesítések",
      "totalCaption": "{0} sorok futó összesítések",
      "grandTotalCaption": "{0} sorok futó összesítések"
    },
    "index": {
      "caption": "Mutató",
      "totalCaption": "{0} mutatója",
      "grandTotalCaption": "{0} mutatója"
    },
    "none": {
      "caption": "Nincs elérhető számítási érték"
    }
  },
  "messages": {
    "error": "Hiba!",
    "warning": "Figyelem!",
    "limitation": "Korlátozás!",
    "browse": "Tallózás",
    "confirmation": "Megerősítés",
    "reportFileType": "Flexmonster riport fájl",
    "loading": "Töltés...",
    "loadingConfiguration": "",
    "loadingData": "Adatok betöltése...",
    "loadingMapping": "Térkép betöltése...",
    "waiting": "Válaszra vár {0} másodperce.",
    "progress": "{0}K",
    "progressKnown": "Betöltve {0} KB a(z) {1} KB",
    "progressUnknown": "Betöltve {0} KB",
    "sortingMembers": "Tagok rendezése...",
    "analyzing": "Adatok feldolgozása...",
    "analyzingProgress": "{0} adatsor a(z) {1}-ból ({2}%)",
    "analyzingRecords": "{0}% adatsorok",
    "saving": "Mentés...",
    "loadingDimensions": "Dimenziók betöltése...",
    "loadingHierarchies": "Hierarchiák betöltése...",
    "loadingMeasures": "Méretek betöltése...",
    "loadingKPIs": "KPI-ok betöltése...",
    "loadingMembers": "Tagok betöltése...",
    "loadingLevels": "Szintek betöltése...",
    "loadingProperties": "Tulajdonságok betöltése...",
    "fullscreen": "Megnyitja a riportot teljes méretben?",
    "exportComplete": "Az adatok exportálhatóak, mentéshez kattintson a \"Mentés\" gombra!",
    "exportProgress": "Adatok kinyerése folyamatban...",
    "exportError": "Váratlan hiba történt. Az exportálás sikertelen.",
    "generatingPDF": "PDF generálása folyamatban",
    "pleaseWait": "Kérem, várjon!",
    "pagesWereGenerated": "__pages were generated.",
    "uploading": "Feltöltés...",
    "cantSaveFile": "Fájl mentése nem lehetséges",
    "cantSaveToClipboard": "Hiba: a vágólap nem elérhető.",
    "saveReportToFile": "A riport mentésre kész, a mentéshez kattintson a \"Mentés\" gombra!",
    "loadReportFromFile": "Select report file to be loaded.",
    "inputNewName": "Adjon meg új nevet!",
    "inputReportName": "Kérem, adja meg a riport nevét!",
    "invalidDataSource": "Érvénytelen adatforrás vagy katalógus, kérem, ellenőrizze ezeket!",
    "dataStreamError": "A '{0}' betöltése során az adatfolyamban hiba lépett fel",
    "unableToOpenFile": "A {0} fájlt nem lehet megnyitni.<br/><br/>A megadott fájl nem létezik, vagy hiányzik az 'Access-Control-Allow-Origin' header a forrásnál.",
    "errorTextMessage": "</br>Részletek: '{0}'",
    "unableTwoFileBrowsingSessions": "A \"Fájl tallózása\" ablak már meg van nyitva",
    "inappropriateFileFormat": "Nem megengedett formátumú a megadott fájl",
    "invalidJSONdata": "A JSON adat érvénytelen",
    "wrongFormulaFormat": "Formailag nem megfelelő a képlet, kérem, ellenőrizze",
    "wrongUniqueName": "A <b>'{0}'</b> egyedi névvel rendelkező mező nincs megadva.",
    "excelCsvChartsExportError": "Diagramok Microsoft Excel vagy CSV formátumba történő kinyerése nem megengedett",
    "excelPdfExportLimitation": "Microsoft Excel vagy PDF fájlba történő exportálás ebben a verzióban nem elérhető",
    "excelExportLimitation": "Exportálás ebben a verzióban nem elérhető",
    "noDataAvailable": "Az adatforrás üres, kérem.",
    "saveDataToFile": "Az adatok mentésre készek, a mentéshez kattintson a \"Mentés\" gombra!",
    "dataWasUpdated": "A szerveren található adatforrás frissült. Szeretné frissíteni a riportot?",
    "cantConnectToAccelerator": "Nem sikerült kapcsolódni az adatforráshoz. Kérem, ellenőrizze, hogy a \"Flexmonster Accelerator\" fut-e!",
    "ocsvIncompatible": "Nem sikerült az adatforrás beolvasása. Úgy tűnik, hogy újabb verzióval történt az OCSV fájl tömörítése. Kérem, frissítse a komponenst a {0} számú vagy frissebb verzióra!",
    "unknownError": "Ismeretlen hiba történt",
    "invalidReportFormat": "Nem megfelelő riport formátum vagy a fájl nem elérhető",
    "invalidReportFormat2": "Invalid report format. 'dataSource' property is required.",
    "csvHeaderParsingError": "CSV header értelmezése\\ felbontása közben hiba lépett fel",
    "tooManyColumnsInClassicMode": "Az oszlopok száma túl sok a klasszikus nézethez. Váltás kompakt módra.",
    "cantExpand": "Néhány mező nem bővíthető. Kérjük, szűkítse meg az adatkészletet.",
    "cantExpandTitle": "Az adatkészlet túl nagy",
    "selectFile": "Válassza ki a feltöltendő adatfájlt.",
    "flatTableIsNotSupported": "A lapos tábla nem támogatott {0} adatforráshoz.",
    "enterGroupNamePrompt": "Kérjük, adja meg a csoport nevét:",
    "exportFontLoadingError": "Failed to load the font. An unexpected error occurred.",
    "api": {
      "incorrectUrl": "Egyéni adatforrás API: az 'url' paraméter hibás típusa. <br/> <br/>",
      "errorZeroStatus": "Nem lehet csatlakozni az '<u> <a> <a href='{0}'> {0} </a> </u>' egyéni adatforrás API végponthoz. <br/> <br/> Ellenőrizze az alábbiakat: <br/> - ellenőrizze, hogy az URL helyes-e <br/> - engedélyezze a CORS-t <br/> - ellenőrizze a böngésző konzolján esetleges hibákat",
      "error404Status": "Nem lehet csatlakozni az '<u> <a> <a href='{0}'> {0} </a> </u>' egyéni adatforrás API végponthoz. <br/> <br/> Ellenőrizze az alábbiakat: <br/> - ellenőrizze, hogy az URL helyes-e. <br/> - ellenőrizze, hogy a végpont feldolgozza a POST kéréseket",
      "error400Status": "Egyéni adatforrás API: hiba kérés a '<u> <a href='{0}'> {0} </a> </u>' oldalon. <br/> <br/>",
      "error500Status": "Egyéni adatforrás API: szerverhiba a '<u> <a href='{0}'> {0} </a> </u>' -on. <br/> <br/>",
      "selectRequestError": "Egyéni adatforrás API: válassza ki a kérelmet. <br/> <br/> A végpont '<u> <a href='{0}'> {0} </a> </u>' válasz nem megfelelő formátumban van.",
      "selectDrillThroughError": "Egyéni adatforrás API: válasszon átfedési nézetet. <br/> <br/> A végpont '<u> <a href='{0}'> {0} </a> </u>' válasz helytelen formátumban van.",
      "serverOutdated": "Egyéni adatforrás API: a flexmonster.js és a szerver API verziói nem kompatibilisek. <br/> <br/> A szerver API elavult. Kérjük, frissítse a '<u> <a href='{0}'> {0} </a> </u>' kiszolgáló API-ját a minimálisan szükséges verzióra: {1}",
      "clientOutdated": "Egyéni adatforrás API: a flexmonster.js és a szerver API verziói nem kompatibilisek. <br/> <br/> A flexmonster.js elavult. Kérjük, frissítse a flexmonster.js fájlt a minimálisan szükséges verzióra: {0}",
      "fieldsRequestError": "Egyéni adatforrás API: mezők kérése. <br/> <br/> A végpont '<u> <a href='{0}'> {0} </a> </u>' válasz hibás formátumban van.",
      "membersRequestError": "Egyéni adatforrás API: a tagok kérik. <br/> <br/> A végpont '<u> <a href='{0}'> {0} </a> </u>' válasz nem megfelelő formátumban van."
    }
  },
  "kpis": {
    "kpis": "KPI-ok",
    "value": "Érték",
    "goal": "Cél",
    "trend": "Trend",
    "status": "Státusz"
  },
  "buttons": {
    "ok": "OK",
    "apply": "Alkalmaz",
    "cancel": "Mégsem",
    "save": "Mentés",
    "clear": "Törlés",
    "select": "Kiválaszt",
    "yes": "Igen",
    "no": "Nem"
  },
  "contextMenu": {
    "clearSorting": "Rendezés törlése",
    "collapse": "Összecsukás",
    "drillThrough": "Aláfúrás",
    "expand": "Kinyitás",
    "openFilter": "Szűrők megnyitása",
    "filterBy": "Szűrők <b>{0}</b>",
    "removeField": "Távolítsa el a mezőt",
    "removeMeasure": "Az érték eltávolítása",
    "sortColumnAsc": "Oszlop növekvő sorrendbe rendezése",
    "sortColumnDesc": "Oszlop csökkenő sorrendbe rendezése",
    "sortRowAsc": "Sor növekvő sorrendbe rendezése",
    "sortRowDesc": "Sor csökkenő sorrendbe rendezése",
    "aggregation": "Összesítése",
    "properties": "Tulajdonságok",
    "editFormula": "Szerkesztés <b>{0}</b>",
    "moveToRows": "Lépjen sorokba",
    "moveToColumns": "Lépjen az oszlopokra",
    "moveToReportFilters": "Lépjen szűrőkre",
    "conditionalFormatting": "Feltételes formázás",
    "numberFormatting": "Cellaformázás",
    "showProperty": "Előadás <b>{0}</b>",
    "hideProperty": "Elrejt <b>{0}</b>",
    "groupMembers": "Csoporttagok",
    "ungroupMembers": "A tagok csoportosítása"
  },
  "date": {
    "year": "Év",
    "quarter": "Negyedév",
    "month": "Hónap",
    "day": "Nap"
  },
  "quarters": {
    "q1": "1. negyedév",
    "q2": "2. negyedév",
    "q3": "3. negyedév",
    "q4": "4. negyedév"
  },
  "months": {
    "january": "Január",
    "february": "Február",
    "march": "Március",
    "april": "Április",
    "may": "Május",
    "june": "Június",
    "july": "Július",
    "august": "Augusztus",
    "september": "Szeptember",
    "october": "Október",
    "november": "November",
    "december": "December"
  },
  "monthsShort": {
    "january": "Jan.",
    "february": "Feb.",
    "march": "Márc.",
    "april": "Ápr.",
    "may": "Máj.",
    "june": "Jún.",
    "july": "Júl.",
    "august": "Aug.",
    "september": "Szept.",
    "october": "Oct.",
    "november": "Nov.",
    "december": "Dec."
  },
  "weekdays": {
    "first": "Vasárnap",
    "second": "Hétfő",
    "third": "Kedd",
    "fourth": "Szerda",
    "fifth": "Csütörtök",
    "sixth": "Péntek",
    "seventh": "Szombat"
  },
  "weekdaysShort": {
    "first": "V",
    "second": "H",
    "third": "K",
    "fourth": "Sze",
    "fifth": "Cs",
    "sixth": "P",
    "seventh": "Szo"
  },
  "toolbar": {
    "connect": "Csatlakozás",
    "connect_local_csv": "CSV ezen a gépen",
    "connect_local_ocsv": "OCSV ezen a gépen",
    "connect_local_json": "JSON ezen a gépen",
    "connect_remote_csv": "CSV távoli gépen",
    "connect_remote_csv_mobile": "CSV",
    "connect_remote_json": "JSON távoli gépen",
    "connect_remote_json_mobile": "JSON",
    "connect_olap": "OLAP-hoz (XMLA)",
    "connect_olap_mobile": "OLAP",
    "connect_elastic": "Elasticsearch",
    "connect_elastic_mobile": "Elastic",
    "open": "Megnyitás",
    "local_report": "Riport ezen a gépen",
    "remote_report": "Riport távoli gépen",
    "remote_report_mobile": "Riport",
    "save": "Mentés",
    "load_json": "JSON riport",
    "grid": "Táblázat",
    "grid_flat": "Denormalizált nézet",
    "grid_classic": "Klasszikus nézet",
    "grid_compact": "Kompakt nézet",
    "charts": "Diagramok",
    "charts_column": "Oszlop",
    "charts_bar_horizontal": "Sáv",
    "charts_line": "Vonal",
    "charts_scatter": "Pont",
    "charts_pie": "Kör",
    "charts_stacked_column": "Halmozott oszlop",
    "charts_column_line": "Oszlop és vonal",
    "charts_multiple": "Több érték megjelenítése",
    "charts_multiple_disabled": "Több érték nem jeleníthető meg",
    "format": "Formátum",
    "format_cells": "Cellaformázás",
    "format_cells_mobile": "Formátum",
    "conditional_formatting": "Feltételes formázás",
    "conditional_formatting_mobile": "Feltételes",
    "options": "Beállítások",
    "fullscreen": "Teljes képernyő",
    "minimize": "Kis méret",
    "export": "Export",
    "export_print": "Nyomtatás",
    "export_html": "HTML",
    "export_csv": "CSV",
    "export_excel": "Excel",
    "export_image": "Képként",
    "export_pdf": "PDF",
    "fields": "Mezők",
    "ok": "OK",
    "apply": "Alkalmaz",
    "done": "Kész",
    "cancel": "Mégsem",
    "value": "Érték",
    "delete": "Törlés",
    "if": "Ha",
    "then": "Akkor",
    "open_remote_csv": "Távoli CSV megnyitása",
    "open_remote_json": "Távoli JSON megnyitása",
    "csv": "CSV",
    "olap_connection_tool": "OLAP kapcsolat kezelő eszköz",
    "select_data_source": "Adatforrás kiválasztása",
    "select_catalog": "Katalógus kiválasztása",
    "select_cube": "Adatkocka kiválasztása",
    "proxy_url": "Proxy URL",
    "data_source_info": "Adatforrás információ",
    "catalog": "Katalógus",
    "cube": "Adatkocka",
    "credentials": "Belépési adatok",
    "username": "Felhasználó név",
    "password": "Jelszó",
    "connect_elastic_title": "Csatlakozzon az Elasticsearch-hez",
    "host_url": "Host URL",
    "index_name": "Index",
    "select_index": "Válassza ki az indexet",
    "open_remote_report": "Távoli riport megnyitása",
    "choose_value": "Válasszon értéket!",
    "text_align": "Szöveg igazítása",
    "align_left": "balra",
    "align_right": "jobbra",
    "none": "nincs",
    "space": "(szóköz)",
    "thousand_separator": "Ezres helyiérték elválasztó",
    "decimal_separator": "Tizedesjel",
    "decimal_places": "Tizedes jegyek száma",
    "currency_symbol": "Mértékegység",
    "positive_currency_format": "Pozitív pénznemformátum",
    "negative_currency_format": "Negatív pénznemformátum",
    "negative_number_format": "Negatív számformátum",
    "currency_align": "Mértékegység helye",
    "null_value": "Hiányzó érték",
    "is_percent": "Százalékban mutat",
    "true_value": "igen",
    "false_value": "nem",
    "confirm_title": "Van néhány mentetlen változása",
    "confirm_message": "A formázás nem kerül alkalmazásra. </br> Kérjük, erősítse meg, hogy az értéket egyébként meg szeretné változtatni.",
    "conditional": "Feltételes",
    "less_than": "kevesebb, mint",
    "less_than_or_equal": "kevesebb, mint vagy egyenlő",
    "greater_than": "nagyobb, mint",
    "greater_than_or_equal": "nagyobb, mint vagy egyenlő",
    "equal_to": "egyenlő",
    "not_equal_to": "nem egyenlő",
    "between": "két érték között",
    "is_empty": "hiányzó érték",
    "all_values": "minden érték",
    "and": "és",
    "and_symbole": "&",
    "no_active_conditions": "Nincsenek aktív feltételek.",
    "add_condition_button": "Feltétel feltétele",
    "cp_text": "Szöveg",
    "cp_highlight": "Kihúzás",
    "layout_options": "Nézet beállítás",
    "layout": "Nézet",
    "compact_view": "Kompakt nézet",
    "classic_view": "Klasszikus nézet",
    "flat_view": "Denormalizált nézet",
    "grand_totals": "Összesen sorok",
    "grand_totals_off": "Ne mutassa az összesen sorokat",
    "grand_totals_on": "Összesen sorok mutatása",
    "grand_totals_on_rows": "Összesen sorok csak sorokra vonatkozóan",
    "grand_totals_on_columns": "Összesen sorok csak oszlopokra vonatkozóan",
    "subtotals": "Részösszegek",
    "subtotals_off": "Ne mutassa a részösszegeket",
    "subtotals_on": "Részösszegek mutatása",
    "subtotals_on_rows": "Részösszegek csak sorokra vonatkozóan",
    "subtotals_on_columns": "Részösszegek csak oszlopokra vonatkozóan",
    "choose_page_orientation": "Válassza ki az oldal tájolását!",
    "landscape": "Fekvő",
    "portrait": "Álló",
    "tooltips": {
      "add_condition": "Feltétel hozzáadaása",
      "remove_condition": "Távolítsa el az állapotot",
      "cp_text_color": "Szöveg szín"
    }
  }
}